pygame_node/__init__.py
pygame_node/event.py
pygame_node/node.py
pygame_node/scene.py
pygame_node/attribute/__init__.py
pygame_node/attribute/event.py
pygame_node/attribute/style.py
pygame_node/data/__init__.py
pygame_node/data/event.py
pygame_node/data/font.py
pygame_node/data/keys.py
pygame_node/data/node.py
pygame_node/data/types.py
pygame_node-0.2.0.dist-info/licenses/LICENSE
pygame_node-0.2.0.dist-info/METADATA
pygame_node-0.2.0.dist-info/WHEEL
pygame_node-0.2.0.dist-info/top_level.txt
pygame_node-0.2.0.dist-info/RECORD
