Metadata-Version: 2.4
Name: pygame_node
Version: 0.2.0
Summary: Use Node structures to manage Pygame resources for rapid game creation and management.
Home-page: https://github.com/Mogui-Hao/PygameNode
Author: MoGui-Hao
Author-email: mogui_hao@outlook.com
Classifier: Programming Language :: Python :: 3
Classifier: Development Status :: 2 - Pre-Alpha
Classifier: Framework :: Buildout :: Extension
Classifier: License :: OSI Approved :: Apache Software License
Requires-Python: >=3.10
License-File: LICENSE
Requires-Dist: pygame~=2.6.1
Dynamic: author
Dynamic: author-email
Dynamic: classifier
Dynamic: description
Dynamic: description-content-type
Dynamic: home-page
Dynamic: license-file
Dynamic: requires-dist
Dynamic: requires-python
Dynamic: summary
